{
  "db_name": "PostgreSQL",
  "query": "\n        UPDATE items\n        SET name = $1, description = $2\n        RETURNING *\n        ",
  "describe": {
    "columns": [
      {
        "ordinal": 0,
        "name": "id",
        "type_info": "Int4"
      },
      {
        "ordinal": 1,
        "name": "name",
        "type_info": "Text"
      },
      {
        "ordinal": 2,
        "name": "description",
        "type_info": "Text"
      }
    ],
    "parameters": {
      "Left": [
        "Text",
        "Text"
      ]
    },
    "nullable": [
      false,
      false,
      true
    ]
  },
  "hash": "c8eb640662a36043a76ca82aec60a10ec3b542f58fc0db5456dcdd8654163b16"
}
